axisem3dshapes/__init__.py
axisem3dshapes/cylinder.py
axisem3dshapes/ellipsoid.py
axisem3dshapes/global.py
axisem3dshapes/injector.py
axisem3dshapes/model.py
axisem3dshapes/object.py
axisem3dshapes/slab.py
axisem3dshapes/sphere.py
axisem3Dshapes-1.0.3.dist-info/LICENSE
axisem3Dshapes-1.0.3.dist-info/METADATA
axisem3Dshapes-1.0.3.dist-info/WHEEL
axisem3Dshapes-1.0.3.dist-info/top_level.txt
axisem3Dshapes-1.0.3.dist-info/RECORD
