Metadata-Version: 2.1
Name: axisem3Dshapes
Version: 1.0.3
Summary: 3D model shapes for AxiSEM-3D
Home-page: https://github.com/williameaton/axisem3d-shapes/blob/main/README.md
Author: W Eaton
Author-email: weaton@princeton.edu
License: UNKNOWN
Project-URL: Bug Tracker, https://github.com/williameaton/axisem3d-shapes/issues
Platform: UNKNOWN
Classifier: Programming Language :: Python :: 3
Classifier: Operating System :: OS Independent
Requires-Python: >=3.8
License-File: LICENSE
